[
 {
  "No": "1",
  "Mag": 9.5,
  "Location": "Bio-Bio, Chile",
  "AlternativeName": "Valdivia Earthquake",
  "Date": "05\/22\/1960",
  "Time": "19:11",
  "Latitude": "-41.5666667",
  "Longitude": "-73.68333333333334",
  "References": "Kanamori & Anderson, 1975"
 },
 {
  "No": "2",
  "Mag": 9.2,
  "Location": "Southern Alaska",
  "AlternativeName": "Good Friday Earthquake",
  "Date": "03\/28\/1964",
  "Time": "3:36",
  "Latitude": "61.5166667",
  "Longitude": "-147.56666666666666",
  "References": "Kanamori & Anderson, 1975"
 },
 {
  "No": "3",
  "Mag": 9.1,
  "Location": "Off the West Coast of Northern Sumatra",
  "AlternativeName": "Sumatra-Andaman Islands Earthquake, Indian Ocean Earthquake",
  "Date": "12\/26\/2004",
  "Time": "0:58",
  "Latitude": "3.5",
  "Longitude": "96.63333333333334",
  "References": "Duputel et al., 2012"
 },
 {
  "No": "4",
  "Mag": 9.1,
  "Location": "Near the East Coast of Honshu, Japan",
  "AlternativeName": "Tohoku Earthquake",
  "Date": "03\/11\/2011",
  "Time": "5:46",
  "Latitude": "38.5",
  "Longitude": "142.61666666666667",
  "References": "Duputel et al., 2012"
 },
 {
  "No": "5",
  "Mag": 9,
  "Location": "Off the East Coast of the Kamchatka Peninsula, Russia",
  "AlternativeName": "Kamchatka, Russia",
  "Date": "11\/04\/1952",
  "Time": "16:58",
  "Latitude": "53.0333333",
  "Longitude": "160.3",
  "References": "Kanamori, 1976"
 },
 {
  "No": "6",
  "Mag": 8.8,
  "Location": "Offshore Bio-Bio, Chile",
  "AlternativeName": "Maule Earthquake",
  "Date": "02\/27\/2010",
  "Time": "6:34",
  "Latitude": "-36.2",
  "Longitude": "-73.5",
  "References": "Duputel et al., 2012"
 },
 {
  "No": "7",
  "Mag": 8.8,
  "Location": "Near the Coast of Ecuador",
  "AlternativeName": "1906 Ecuador–Colombia Earthquake",
  "Date": "01\/31\/1906",
  "Time": "15:36",
  "Latitude": "1.6",
  "Longitude": "-79.61666666666666",
  "References": "Kanamori, 1977"
 },
 {
  "No": "8",
  "Mag": 8.7,
  "Location": "Rat Islands, Aleutian Islands, Alaska",
  "AlternativeName": "Rat Islands Earthquake",
  "Date": "02\/04\/1965",
  "Time": "5:01",
  "Latitude": "51.4166667",
  "Longitude": "179.2",
  "References": "Kanamori & Anderson, 1975"
 },
 {
  "No": "9",
  "Mag": 8.6,
  "Location": "Eastern Xizang-India border region",
  "AlternativeName": "Assam, Tibet",
  "Date": "08\/15\/1950",
  "Time": "14:09",
  "Latitude": "28.6",
  "Longitude": "96.75",
  "References": "Kanamori, 1977"
 },
 {
  "No": "10",
  "Mag": 8.6,
  "Location": "Off the West Coast of Northern Sumatra",
  "AlternativeName": "–",
  "Date": "04\/11\/2012",
  "Time": "8:39",
  "Latitude": "2.55",
  "Longitude": "93.1",
  "References": "Duputel et al., 2012"
 },
 {
  "No": "11",
  "Mag": 8.6,
  "Location": "Northern Sumatra, Indonesia",
  "AlternativeName": "Nias Earthquake",
  "Date": "03\/28\/2005",
  "Time": "16:10",
  "Latitude": "2.15",
  "Longitude": "97.18333333333334",
  "References": "NEIC"
 },
 {
  "No": "12",
  "Mag": 8.6,
  "Location": "Andrean of Islands, Aleutian Islands, Alaska",
  "AlternativeName": "–",
  "Date": "03\/09\/1957",
  "Time": "14:23",
  "Latitude": "51.8333333",
  "Longitude": "-176.05",
  "References": "Johnson et al., 1994"
 },
 {
  "No": "13",
  "Mag": 8.6,
  "Location": "South of Alaska",
  "AlternativeName": "Unimak Island Earthquake, Alaska",
  "Date": "04\/01\/1946",
  "Time": "12:29",
  "Latitude": "61.2",
  "Longitude": "-175.86666666666667",
  "References": "Lopez & Okal, 2006"
 },
 {
  "No": "14",
  "Mag": 8.5,
  "Location": "Banda Sea",
  "AlternativeName": "–",
  "Date": "02\/01\/1938",
  "Time": "19:04",
  "Latitude": "-5.75",
  "Longitude": "136.23333333333332",
  "References": "Okal & Reymond, 2003"
 },
 {
  "No": "15",
  "Mag": 8.5,
  "Location": "Atacama, Chile",
  "AlternativeName": "Chile-Argentina Border",
  "Date": "11\/11\/1922",
  "Time": "4:33",
  "Latitude": "-32.8833333",
  "Longitude": "-83.2",
  "References": "Kanamori, 1977"
 },
 {
  "No": "16",
  "Mag": 8.5,
  "Location": "Kuril Islands",
  "AlternativeName": "–",
  "Date": "10\/13\/1963",
  "Time": "5:18",
  "Latitude": "58.5333333",
  "Longitude": "157.05",
  "References": "Kanamori & Anderson, 1975"
 },
 {
  "No": "17",
  "Mag": 8.4,
  "Location": "Near the East Coast of Kamchatka Peninsula, Russia",
  "AlternativeName": "Kamchatka, Russia",
  "Date": "02\/03\/1923",
  "Time": "16:02",
  "Latitude": "62.1",
  "Longitude": "167.86666666666667",
  "References": "Okal, 1992"
 },
 {
  "No": "18",
  "Mag": 8.4,
  "Location": "Southern Sumatra, Indonesia",
  "AlternativeName": "–",
  "Date": "09\/12\/2007",
  "Time": "11:10",
  "Latitude": "-11.3",
  "Longitude": "107.11666666666666",
  "References": "NEIC"
 },
 {
  "No": "19",
  "Mag": 8.4,
  "Location": "Near the Coast of Southern Peru",
  "AlternativeName": "Arequipa, Peru Earthquake",
  "Date": "06\/23\/2001",
  "Time": "20:33",
  "Latitude": "-20.4166667",
  "Longitude": "-83.69999972222223",
  "References": "Duputel et al., 2012"
 },
 {
  "No": "20",
  "Mag": 8.4,
  "Location": "Off the East Coast of Honshu, Japan",
  "AlternativeName": "Sanriku, Japan",
  "Date": "03\/02\/1933",
  "Time": "17:31",
  "Latitude": "42.4833333",
  "Longitude": "153.83333333333334",
  "References": "Kanamori, 1971"
 }
]